{
  "gitSyncId": "69e74cca833ce3305690f08f_854ddfc7-7260-489a-b80b-970d70bc8ac9",
  "id": "CustomerData_appInit.init",
  "pluginId": "js-plugin",
  "pluginType": "JS",
  "unpublishedAction": {
    "actionConfiguration": {
      "encodeParamsToggle": true,
      "jsArguments": [],
      "paginationType": "NONE",
      "timeoutInMillisecond": 10000
    },
    "collectionId": "CustomerData_appInit",
    "confirmBeforeExecute": false,
    "datasource": {
      "isAutoGenerated": false,
      "name": "UNUSED_DATASOURCE",
      "pluginId": "js-plugin"
    },
    "dynamicBindingPathList": [
      {
        "key": "body"
      }
    ],
    "fullyQualifiedName": "appInit.init",
    "name": "init",
    "pageId": "CustomerData",
    "runBehaviour": "ON_PAGE_LOAD",
    "userSetOnLoad": true
  }
}