{
  "animateLoading": true,
  "borderRadius": "0.375rem",
  "bottomRow": 749,
  "boxShadow": "none",
  "canEscapeKeyClose": true,
  "canOutsideClickClose": true,
  "children": [
    {
      "borderRadius": "{{appsmith.theme.borderRadius.appBorderRadius}}",
      "bottomRow": 730,
      "boxShadow": "{{appsmith.theme.boxShadow.appBoxShadow}}",
      "canExtend": true,
      "detachFromLayout": true,
      "dynamicBindingPathList": [
        {
          "key": "borderRadius"
        },
        {
          "key": "boxShadow"
        }
      ],
      "dynamicHeight": "AUTO_HEIGHT",
      "flexLayers": [],
      "isDisabled": false,
      "isLoading": false,
      "isVisible": true,
      "key": "01gudekou9",
      "leftColumn": 0,
      "maxDynamicHeight": 9000,
      "minDynamicHeight": 4,
      "minHeight": 730,
      "minWidth": 450,
      "mobileBottomRow": 240,
      "mobileLeftColumn": 0,
      "mobileRightColumn": 401.25,
      "mobileTopRow": 0,
      "needsErrorInfo": false,
      "parentColumnSpace": 1,
      "parentId": "4mmht41cko",
      "parentRowSpace": 1,
      "renderMode": "CANVAS",
      "responsiveBehavior": "fill",
      "rightColumn": 401.25,
      "shouldScrollContents": false,
      "topRow": 0,
      "type": "CANVAS_WIDGET",
      "version": 1,
      "widgetId": "yxchheu2tb",
      "widgetName": "Canvas1"
    }
  ],
  "detachFromLayout": true,
  "dynamicBindingPathList": [],
  "dynamicHeight": "AUTO_HEIGHT",
  "dynamicTriggerPathList": [
    {
      "key": "onClose"
    }
  ],
  "height": 730,
  "isCanvas": true,
  "isLoading": false,
  "key": "lbuqzk3ujx",
  "leftColumn": 21,
  "maxDynamicHeight": 9000,
  "minDynamicHeight": 10,
  "minHeight": 730,
  "mobileBottomRow": 43,
  "mobileLeftColumn": 21,
  "mobileRightColumn": 45,
  "mobileTopRow": 19,
  "needsErrorInfo": false,
  "onClose": "{{resetWidget(\"tbl_customers\", true);}}",
  "originalBottomRow": 749,
  "originalTopRow": 19,
  "parentColumnSpace": 16.71875,
  "parentId": "0",
  "parentRowSpace": 10,
  "renderMode": "CANVAS",
  "rightColumn": 45,
  "shouldScrollContents": true,
  "topRow": 19,
  "type": "MODAL_WIDGET",
  "version": 2,
  "widgetId": "4mmht41cko",
  "widgetName": "mdl_customerDetails",
  "width": 1015.3999999999999
}